cobrak/__init__.py
cobrak/_efms.py
cobrak/alphafold_db_functionality.py
cobrak/bigg_metabolites_functionality.py
cobrak/brenda_functionality.py
cobrak/cobrapy_model_functionality.py
cobrak/constants.py
cobrak/dataclasses.py
cobrak/equilibrator_functionality.py
cobrak/evolution.py
cobrak/example_models.py
cobrak/expasy_functionality.py
cobrak/genetic.py
cobrak/io.py
cobrak/lps.py
cobrak/metanetx_functionality.py
cobrak/model_instantiation.py
cobrak/molmass_functionality.py
cobrak/ncbi_taxonomy_functionality.py
cobrak/nlps.py
cobrak/plotting.py
cobrak/printing.py
cobrak/pyomo_functionality.py
cobrak/sabio_rk_functionality.py
cobrak/spreadsheet_functionality.py
cobrak/standard_solvers.py
cobrak/tellurium_functionality.py
cobrak/thermokinetic_data_retrieval.py
cobrak/uniprot_functionality.py
cobrak/utilities.py
cobrak-0.0.8.dist-info/licenses/LICENSE
cobrak-0.0.8.dist-info/METADATA
cobrak-0.0.8.dist-info/WHEEL
cobrak-0.0.8.dist-info/top_level.txt
cobrak-0.0.8.dist-info/RECORD
