Metadata-Version: 2.4
Name: cobrak
Version: 0.0.8
Summary: Implementation of COBRA-k
Author: Pavlos Stephanos Bekiaris
Project-URL: Homepage, https://github.com/klamt-lab/cobrak
Project-URL: Issues, https://github.com/klamt-lab/cobrak/issues
Classifier: Programming Language :: Python :: 3
Classifier: License :: OSI Approved :: Apache Software License
Classifier: Operating System :: OS Independent
Requires-Python: ==3.10.*
License-File: LICENSE
Requires-Dist: dataclasses-json
Requires-Dist: matplotlib
Requires-Dist: numpy
Requires-Dist: openpyxl
Requires-Dist: pyomo
Requires-Dist: requests
Requires-Dist: pyscipopt
Requires-Dist: cobra
Requires-Dist: equilibrator_api
Requires-Dist: tellurium
Requires-Dist: joblib
Requires-Dist: rich
Requires-Dist: pydantic
Requires-Dist: highspy
Requires-Dist: molmass
Dynamic: license-file
